CHANGES
LICENSE
README
ez_setup.py
setup.cfg
setup.py
pyThesaurus/Concept.py
pyThesaurus/README.txt
pyThesaurus/TODO.txt
pyThesaurus/Thesaurus.py
pyThesaurus/__init__.py
pyThesaurus/config.py
pyThesaurus/io.py
pyThesaurus/ioDing.py
pyThesaurus/ioSKOSCore.py
pyThesaurus/release.txt
pyThesaurus/version.txt
pyThesaurus.egg-info/PKG-INFO
pyThesaurus.egg-info/SOURCES.txt
pyThesaurus.egg-info/dependency_links.txt
pyThesaurus.egg-info/top_level.txt
pyThesaurus/tests/__init__.py
pyThesaurus/tests/test_heavy.py
pyThesaurus/tests/test_io.py
pyThesaurus/tests/test_persistence.py
pyThesaurus/tests/test_skos.py
pyThesaurus/tests/test_thesauri.py
pyThesaurus/tests/data/open_thesaurus_es.txt
pyThesaurus/tests/data/sample000.rdf
pyThesaurus/tests/data/sample000.txt
pyThesaurus/tests/data/sample001.rdf
pyThesaurus/tests/data/sample001.txt
pyThesaurus/tests/data/sample002.rdf
pyThesaurus/tests/data/sample002.txt
pyThesaurus/tests/data/sample003.rdf
pyThesaurus/tests/data/sample004.rdf
pyThesaurus/tests/data/sample005.rdf
pyThesaurus/tests/data/sample006.rdf
pyThesaurus/tests/data/sample007.rdf
pyThesaurus/tests/data/sample008.rdf
pyThesaurus/tests/data/sample009.rdf
pyThesaurus/tests/data/sample010.rdf
pyThesaurus/tests/data/sample011.rdf
pyThesaurus/tests/data/sample012.rdf
pyThesaurus/tests/data/sample013.rdf
pyThesaurus/tests/data/sample014.rdf
pyThesaurus/tests/data/sample015.rdf
pyThesaurus/tests/data/ukat_concepts.rdf