Metadata-Version: 1.0
Name: pyThesaurus
Version: 1.1-dev-r308
Summary: Ontology module with Thesaurus administration model. Developed for Platecom project.
Home-page: www.platecom.com
Author: Inter-Cultura Consultora SRL - Ibai Sistemas SA - Eusko Ikaskuntza-Sociedad de Estudios Vascos
Author-email: dev@inter-cultura.com
License: GPL
Keywords: thesaurus,thesauri,ontology
Platform: UNKNOWN
Classifier: Programming Language :: Python
Classifier: Topic :: Software Development :: Libraries :: Python Modules
